MANIFEST.in
README.md
pyproject.toml
setup.py
asl_pepper_responsive.egg-info/PKG-INFO
asl_pepper_responsive.egg-info/SOURCES.txt
asl_pepper_responsive.egg-info/dependency_links.txt
asl_pepper_responsive.egg-info/requires.txt
asl_pepper_responsive.egg-info/top_level.txt
lib_clustering/clustering.cpp
lib_clustering/clustering.pyx
lib_dwa/dynamic_window.cpp
lib_dwa/dynamic_window.pyx